act_vending.v
// trial-1
module act_vending (clk,rst,input10,input50,inputa0,selectcan1,selectcan2,selectcan3,can1,can2,can3,chng);
   input clk, rst, input10,input50,inputa0,selectcan1,selectcan2,selectcan3;
   output can1,can2,can3;  // 是否可以购买饮料的信号
   output [4:0] chng; // 找零信号

   parameter s0 = 2'b00,
             s1 = 2'b01,
             s2 = 2'b10;

   reg can1,can2,can3;
   reg [4:0] chng;
   reg [1:0] state, next_state;
   reg [4:0] amount; // 金额寄存器

   // Next state logic
   always @(state or input10 or input50 or inputa0 or rst or selectcan1 or selectcan2 or selectcan3)
      begin
        case (state)
            s0: 
              // if(input10 | input50 | inputa0)
                next_state <= s1;
              // else
              //   next_state <= s0;
             
            s1: 
            if(input10 | input50 | inputa0 | rst)
              next_state <= s1;
            else 
              state <= s2;

            s2:
              if(rst)
                next_state <= s0;
              else if((selectcan1 && (amount >= 12)) || (selectcan2 && (amount >= 13)) || (selectcan3 && (amount >= 14)))
                next_state <= s2;
              else
                next_state <= s1;

            default: next_state <= 2'b00;
        endcase

      end

   // Current state logic
   always @(posedge clk or negedge rst)
      begin
          state <= next_state;
      end

   // Output logic
   always @(state or selectcan1 or selectcan2 or selectcan3)
      begin
        case (state)
            s0: begin
                amount <= 0;
            end
            s1: begin
                if(input10)
                begin
                  amount <= amount + 1;
                end
                else if(input50)
                begin
                  amount <= amount + 5;
                end
                else if(inputa0)
                begin
                  amount <= amount + 10;
                end
            end
            s2: begin
                if(rst)begin
                  chng <= amount;
                  end
                else if(selectcan1 && (amount >= 12))
                  begin
                    can1 <= 1;
                    amount = amount - 12;
                    chng = amount;
                  end 
                else if(selectcan2 && (amount >= 13))
                  begin
                    can2 <= 1;
                    amount = amount - 13;
                    chng = amount;
                  end 
                else if(selectcan3 && (amount >= 14))
                  begin
                    can3 <= 1;
                    amount = amount - 14;
                    chng = amount;
                  end 
                else
                begin
                  can1 <= 0;
                  can2 <= 0;
                  can3 <= 0;
                  chng <= 0;
                end

            end
        endcase
      end

endmodule

t_act_vending.v
// Test pattern trial-1
`timescale 1ns / 10ps
module t_act_vending;
  reg clk, rst, input10, input50, inputa0, selectcan1, selectcan2, selectcan3;
  wire can1,can2,can3;
  wire [4:0] chng;


  // Clock
  initial clk = 0;
  always
    #5 clk = ~clk;

  initial
    begin
      $dumpfile("act_vending.vcd");
      $dumpvars(0,t_act_vending);
      $monitor("%t input10=%b, input50=%b, inputa0=%b,selectcan1=%b,selectcan2=%b,selectcan3=%b, state = %b", 
               $time, input10, input50,inputa0,selectcan1,selectcan2,selectcan3,act_vending1.state);
      
      rst <= 0; input10 <=0; input50 <=0; inputa0 <=0; selectcan1 <=0; selectcan2<=0; selectcan3<=0;
      
      #10 

      #10 inputa0 = 1;
      #10 inputa0 = 0;
      #20 inputa0 = 1; 
      #10 inputa0 = 0;
      #20 input50 = 0; 
      #10 input50 = 0;
      #40 selectcan2 = 1; 
      #40 selectcan2 = 0;

      #100
      $finish;
    end

   act_vending act_vending1(clk,rst,input10,input50,inputa0,selectcan1,selectcan2,selectcan3,can1,can2,can3,chng);
endmodule

act_vending.vcd
$date
	Tue Apr  9 20:48:56 2024
$end
$version
	Icarus Verilog
$end
$timescale
	10ps
$end
$scope module t_act_vending $end
$var wire 5 ! chng [4:0] $end
$var wire 1 " can3 $end
$var wire 1 # can2 $end
$var wire 1 $ can1 $end
$var reg 1 % clk $end
$var reg 1 & input10 $end
$var reg 1 ' input50 $end
$var reg 1 ( inputa0 $end
$var reg 1 ) rst $end
$var reg 1 * selectcan1 $end
$var reg 1 + selectcan2 $end
$var reg 1 , selectcan3 $end
$scope module act_vending1 $end
$var wire 1 % clk $end
$var wire 1 & input10 $end
$var wire 1 ' input50 $end
$var wire 1 ( inputa0 $end
$var wire 1 ) rst $end
$var wire 1 * selectcan1 $end
$var wire 1 + selectcan2 $end
$var wire 1 , selectcan3 $end
$var parameter 2 - s0 $end
$var parameter 2 . s1 $end
$var parameter 2 / s2 $end
$var reg 5 0 amount [4:0] $end
$var reg 1 $ can1 $end
$var reg 1 # can2 $end
$var reg 1 " can3 $end
$var reg 5 1 chng [4:0] $end
$var reg 2 2 next_state [1:0] $end
$var reg 2 3 state [1:0] $end
$upscope $end
$upscope $end
$enddefinitions $end
$comment Show the parameter values. $end
$dumpall
b10 /
b1 .
b0 -
$end
#0
$dumpvars
bx 3
b0 2
bx 1
bx 0
0,
0+
0*
0)
0(
0'
0&
0%
x$
x#
x"
bx !
$end
#500
b0 0
b1 2
b0 3
1%
#1000
0%
#1500
b0 !
b0 1
0"
0#
0$
b10 3
1%
#2000
0%
1(
#2500
b1010 0
b1 3
1%
#3000
b10 3
0%
0(
#3500
b10 3
1%
#4000
0%
#4500
b10 3
1%
#5000
0%
1(
#5500
b10100 0
b1 3
1%
#6000
b10 3
0%
0(
#6500
b10 3
1%
#7000
0%
#7500
b10 3
1%
#8000
0%
#8500
b10 3
1%
#9000
0%
#9500
b10 3
1%
#10000
0%
#10500
b10 3
1%
#11000
0%
#11500
b10 3
1%
#12000
0%
#12500
b10 3
1%
#13000
1#
b10 2
b111 !
b111 1
b111 0
0%
1+
#13500
1%
#14000
0%
#14500
1%
#15000
0%
#15500
1%
#16000
0%
#16500
1%
#17000
b0 !
b0 1
0#
b1 2
0%
0+
#17500
b10 3
1%
#18000
0%
#18500
b10 3
1%
#19000
0%
#19500
b10 3
1%
#20000
0%
#20500
b10 3
1%
#21000
0%
#21500
b10 3
1%
#22000
0%
#22500
b10 3
1%
#23000
0%
#23500
b10 3
1%
#24000
0%
#24500
b10 3
1%
#25000
0%
#25500
b10 3
1%
#26000
0%
#26500
b10 3
1%
